pycupiddb/__init__.py
pycupiddb/client.py
pycupiddb/commands.py
pycupiddb/connection.py
pycupiddb/exceptions.py
pycupiddb-1.4.0.dist-info/LICENSE
pycupiddb-1.4.0.dist-info/METADATA
pycupiddb-1.4.0.dist-info/WHEEL
pycupiddb-1.4.0.dist-info/top_level.txt
pycupiddb-1.4.0.dist-info/RECORD
