Metadata-Version: 2.2
Name: pycupiddb
Version: 1.4.0
Summary: Python client for CupidDB
Author-email: Watt Iamsuri <wiamsuri@gmail.com>
License:                                  Apache License
Project-URL: Homepage, https://github.com/cupiddb/pycupiddb
Keywords: pycupiddb,cupiddb,client,key-value store,in-memory database
Classifier: Programming Language :: Python
Classifier: Programming Language :: Python :: 3 :: Only
Classifier: Programming Language :: Python :: 3.9
Classifier: Programming Language :: Python :: 3.10
Classifier: Programming Language :: Python :: 3.11
Classifier: Programming Language :: Python :: 3.12
Classifier: License :: OSI Approved :: Apache Software License
Classifier: Topic :: Database
Requires-Python: >=3.9
License-File: LICENSE
Requires-Dist: pandas>=1.4.0
Requires-Dist: pyarrow>=14.0.0
Provides-Extra: tests
Requires-Dist: pytest>=8.2.0; extra == "tests"
Requires-Dist: mypy>=1.10.0; extra == "tests"
Requires-Dist: pandas-stubs; extra == "tests"
Requires-Dist: pyarrow-stubs; extra == "tests"
Requires-Dist: pytest-cov>=5.0.0; extra == "tests"
